net_inspect/__init__.py
net_inspect/__main__.py
net_inspect/analysis_plugin.py
net_inspect/api.py
net_inspect/base_info.py
net_inspect/bootstrap.py
net_inspect/cli.py
net_inspect/data.py
net_inspect/domain.py
net_inspect/exception.py
net_inspect/func.py
net_inspect/logger.py
net_inspect/plugin_manager.py
net_inspect/plugins/__init__.py
net_inspect/plugins/analysis_plugin_with_cpu_status.py
net_inspect/plugins/analysis_plugin_with_fan_status.py
net_inspect/plugins/analysis_plugin_with_logger_summary.py
net_inspect/plugins/analysis_plugin_with_memory_status.py
net_inspect/plugins/analysis_plugin_with_power_status.py
net_inspect/plugins/input_plugin_with_console.py
net_inspect/plugins/input_plugin_with_smartone.py
net_inspect/plugins/output_plugin_with_device_list.py
net_inspect/plugins/output_plugin_with_device_warning_logging.py
net_inspect/plugins/output_plugin_with_excel_report.py
net_inspect/plugins/parse_plugin_with_ntc_templates.py
net_inspect/third_party/__init__.py
net_inspect/third_party/excel.py
net_inspect/vendor.py
net_inspect-1.5.3.dist-info/METADATA
net_inspect-1.5.3.dist-info/entry_points.txt
net_inspect-1.5.3.dist-info/WHEEL
net_inspect-1.5.3.dist-info/LICENSE
net_inspect-1.5.3.dist-info/RECORD
