Metadata-Version: 2.1
Name: net-inspect
Version: 1.5.3
Summary: 基于已收集的网络设备信息进行的结构化数据分析框架
Home-page: https://github.com/Elinpf/net_inspect
License: Apache-2.0
Author: Elin
Author-email: 365433079@qq.com
Requires-Python: >=3.7,<4.0
Classifier: License :: OSI Approved :: Apache Software License
Classifier: Programming Language :: Python :: 3
Classifier: Programming Language :: Python :: 3.7
Classifier: Programming Language :: Python :: 3.8
Classifier: Programming Language :: Python :: 3.9
Classifier: Programming Language :: Python :: 3.10
Classifier: Programming Language :: Python :: 3.11
Requires-Dist: loguru (>=0.6.0,<0.7.0)
Requires-Dist: ntc_templates_elinpf (>=3.5.0,<4.0.0)
Requires-Dist: rich_typer (>=0.1.5,<0.2.0)
Project-URL: Repository, https://github.com/Elinpf/net_inspect
